{"legislative_session": "2025", "identifier": "SB 435", "title": "Restore Master's Pay for Teachers and ISP.", "from_organization": "~{\"classification\": \"upper\"}", "classification": ["bill"], "subject": ["APPROPRIATIONS; BUDGETING; EDUCATION; ELEMENTARY EDUCATION; EMPLOYMENT; OCCUPATIONS; PERSONNEL; PUBLIC; PUBLIC INSTRUCTION DEPT.; SALARIES & BENEFITS; SECONDARY EDUCATION; STATE EMPLOYEES; TEACHERS; GOVERNMENT EMPLOYEES"], "abstracts": [], "other_titles": [], "other_identifiers": [], "actions": [{"description": "Ref To Com On Rules and Operations of the Senate", "date": "2025-03-25", "organization_id": "~{\"classification\": \"upper\"}", "classification": ["referral-committee"], "related_entities": []}, {"description": "Passed 1st Reading", "date": "2025-03-25", "organization_id": "~{\"classification\": \"upper\"}", "classification": ["reading-1"], "related_entities": []}, {"description": "Filed", "date": "2025-03-24", "organization_id": "~{\"classification\": \"upper\"}", "classification": ["introduction"], "related_entities": []}], "sponsorships": [{"name": "Grafstein", "classification": "primary", "entity_type": "person", "primary": true, "person_id": "~{\"name\": \"Grafstein\"}", "organization_id": null}, {"name": "Everitt", "classification": "primary", "entity_type": "person", "primary": true, "person_id": "~{\"name\": \"Everitt\"}", "organization_id": null}, {"name": "Bradley", "classification": "cosponsor", "entity_type": "person", "primary": false, "person_id": "~{\"name\": \"Bradley\"}", "organization_id": null}, {"name": "Adcock", "classification": "cosponsor", "entity_type": "person", "primary": false, "person_id": "~{\"name\": \"Adcock\"}", "organization_id": null}, {"name": "Applewhite", "classification": "cosponsor", "entity_type": "person", "primary": false, "person_id": "~{\"name\": \"Applewhite\"}", "organization_id": null}, {"name": "Chaudhuri", "classification": "cosponsor", "entity_type": "person", "primary": false, "person_id": "~{\"name\": \"Chaudhuri\"}", "organization_id": null}, {"name": "Chitlik", "classification": "cosponsor", "entity_type": "person", "primary": false, "person_id": "~{\"name\": \"Chitlik\"}", "organization_id": null}, {"name": "Garrett", "classification": "cosponsor", "entity_type": "person", "primary": false, "person_id": "~{\"name\": \"Garrett\"}", "organization_id": null}, {"name": "Lowe", "classification": "cosponsor", "entity_type": "person", "primary": false, "person_id": "~{\"name\": \"Lowe\"}", "organization_id": null}, {"name": "Mayfield", "classification": "cosponsor", "entity_type": "person", "primary": false, "person_id": "~{\"name\": \"Mayfield\"}", "organization_id": null}, {"name": "Mohammed", "classification": "cosponsor", "entity_type": "person", "primary": false, "person_id": "~{\"name\": \"Mohammed\"}", "organization_id": null}, {"name": "Murdock", "classification": "cosponsor", "entity_type": "person", "primary": false, "person_id": "~{\"name\": \"Murdock\"}", "organization_id": null}, {"name": "Robinson", "classification": "cosponsor", "entity_type": "person", "primary": false, "person_id": "~{\"name\": \"Robinson\"}", "organization_id": null}, {"name": "Salvador", "classification": "cosponsor", "entity_type": "person", "primary": false, "person_id": "~{\"name\": \"Salvador\"}", "organization_id": null}, {"name": "Smith", "classification": "cosponsor", "entity_type": "person", "primary": false, "person_id": "~{\"name\": \"Smith\"}", "organization_id": null}, {"name": "Theodros", "classification": "cosponsor", "entity_type": "person", "primary": false, "person_id": "~{\"name\": \"Theodros\"}", "organization_id": null}, {"name": "Waddell", "classification": "cosponsor", "entity_type": "person", "primary": false, "person_id": "~{\"name\": \"Waddell\"}", "organization_id": null}], "related_bills": [], "versions": [{"note": "Filed", "links": [{"url": "https://www.ncleg.gov/Sessions/2025/Bills/Senate/PDF/S435v0.pdf", "media_type": "application/pdf"}], "date": "", "classification": ""}, {"note": "Edition 1", "links": [{"url": "https://www.ncleg.gov/Sessions/2025/Bills/Senate/PDF/S435v1.pdf", "media_type": "application/pdf"}], "date": "", "classification": ""}], "documents": [], "citations": [], "sources": [{"url": "https://www.ncleg.gov/BillLookUp/2025/S435", "note": ""}], "extras": {}, "jurisdiction": {"id": "ocd-jurisdiction/country:us/state:nc/government", "name": "North Carolina", "classification": "state", "division_id": "ocd-division/country:us/state:nc"}, "scraped_at": "2025-07-28T19:02:45+00:00", "_id": "71fe524a-6be5-11f0-9237-f685d79cdd2c"}