{"legislative_session": "2025", "identifier": "HB 463", "title": "First Responders Mental Health Plan Act.", "from_organization": "~{\"classification\": \"lower\"}", "classification": ["bill"], "subject": ["EMERGENCY SERVICES; HEALTH SERVICES; INSURANCE; INSURANCE DEPT.; INSURANCE", "HEALTH; LOCAL GOVERNMENT; MENTAL HEALTH; PERSONNEL; PUBLIC; STATE EMPLOYEES; GOVERNMENT EMPLOYEES; LOCAL GOVERNMENT EMPLOYEES"], "abstracts": [], "other_titles": [], "other_identifiers": [], "actions": [{"description": "Ref to the Com on Appropriations, if favorable, Rules, Calendar, and Operations of the House", "date": "2025-03-20", "organization_id": "~{\"classification\": \"lower\"}", "classification": ["referral-committee"], "related_entities": []}, {"description": "Passed 1st Reading", "date": "2025-03-20", "organization_id": "~{\"classification\": \"lower\"}", "classification": ["reading-1"], "related_entities": []}, {"description": "Filed", "date": "2025-03-19", "organization_id": "~{\"classification\": \"lower\"}", "classification": ["introduction"], "related_entities": []}], "sponsorships": [{"name": "Clampitt", "classification": "primary", "entity_type": "person", "primary": true, "person_id": "~{\"name\": \"Clampitt\"}", "organization_id": null}, {"name": "Reeder", "classification": "cosponsor", "entity_type": "person", "primary": false, "person_id": "~{\"name\": \"Reeder\"}", "organization_id": null}, {"name": "Ager", "classification": "cosponsor", "entity_type": "person", "primary": false, "person_id": "~{\"name\": \"Ager\"}", "organization_id": null}, {"name": "Belk", "classification": "cosponsor", "entity_type": "person", "primary": false, "person_id": "~{\"name\": \"Belk\"}", "organization_id": null}, {"name": "G. Brown", "classification": "cosponsor", "entity_type": "person", "primary": false, "person_id": "~{\"name\": \"G. Brown\"}", "organization_id": null}, {"name": "Campbell", "classification": "cosponsor", "entity_type": "person", "primary": false, "person_id": "~{\"name\": \"Campbell\"}", "organization_id": null}, {"name": "Cervania", "classification": "cosponsor", "entity_type": "person", "primary": false, "person_id": "~{\"name\": \"Cervania\"}", "organization_id": null}, {"name": "Cotham", "classification": "cosponsor", "entity_type": "person", "primary": false, "person_id": "~{\"name\": \"Cotham\"}", "organization_id": null}, {"name": "Cunningham", "classification": "cosponsor", "entity_type": "person", "primary": false, "person_id": "~{\"name\": \"Cunningham\"}", "organization_id": null}, {"name": "Hawkins", "classification": "cosponsor", "entity_type": "person", "primary": false, "person_id": "~{\"name\": \"Hawkins\"}", "organization_id": null}, {"name": "F. Jackson", "classification": "cosponsor", "entity_type": "person", "primary": false, "person_id": "~{\"name\": \"F. Jackson\"}", "organization_id": null}, {"name": "Logan", "classification": "cosponsor", "entity_type": "person", "primary": false, "person_id": "~{\"name\": \"Logan\"}", "organization_id": null}, {"name": "Longest", "classification": "cosponsor", "entity_type": "person", "primary": false, "person_id": "~{\"name\": \"Longest\"}", "organization_id": null}, {"name": "Majeed", "classification": "cosponsor", "entity_type": "person", "primary": false, "person_id": "~{\"name\": \"Majeed\"}", "organization_id": null}, {"name": "Penny", "classification": "cosponsor", "entity_type": "person", "primary": false, "person_id": "~{\"name\": \"Penny\"}", "organization_id": null}, {"name": "G. Pierce", "classification": "cosponsor", "entity_type": "person", "primary": false, "person_id": "~{\"name\": \"G. Pierce\"}", "organization_id": null}, {"name": "Charles Smith", "classification": "cosponsor", "entity_type": "person", "primary": false, "person_id": "~{\"name\": \"Charles Smith\"}", "organization_id": null}, {"name": "White", "classification": "cosponsor", "entity_type": "person", "primary": false, "person_id": "~{\"name\": \"White\"}", "organization_id": null}], "related_bills": [], "versions": [{"note": "Filed", "links": [{"url": "https://www.ncleg.gov/Sessions/2025/Bills/House/PDF/H463v0.pdf", "media_type": "application/pdf"}], "date": "", "classification": ""}, {"note": "Edition 1", "links": [{"url": "https://www.ncleg.gov/Sessions/2025/Bills/House/PDF/H463v1.pdf", "media_type": "application/pdf"}], "date": "", "classification": ""}], "documents": [], "citations": [], "sources": [{"url": "https://www.ncleg.gov/BillLookUp/2025/H463", "note": ""}], "extras": {}, "jurisdiction": {"id": "ocd-jurisdiction/country:us/state:nc/government", "name": "North Carolina", "classification": "state", "division_id": "ocd-division/country:us/state:nc"}, "scraped_at": "2025-07-28T19:02:56+00:00", "_id": "787934aa-6be5-11f0-9237-f685d79cdd2c"}