{"legislative_session": "2025", "identifier": "HB 977", "title": "Defend NC.", "from_organization": "~{\"classification\": \"lower\"}", "classification": ["bill"], "subject": ["BOARDS; BUDGETING; CITIZENSHIP; CJE & TRAINING STANDARDS COMN.; COLLEGES & UNIVERSITIES; COMMERCE; COMMISSIONS; COUNTIES; DHHS; EDUCATION; EDUCATION", "HEALTH; INTERNATIONAL TRADE; LAW ENFORCEMENT; LAW ENFORCEMENT OFFICERS; LOCAL GOVERNMENT; MEDICAID; PERSONNEL; POVERTY; PUBLIC; RESEARCH; RETAILING; SHERIFFS; SHERIFF'S TRAINING COMN.; SOCIAL SERVICES; STUDIES; TAXATION; TAXES", "SALES & USE; UNC; ALIENS", "STATE BOARD OF; EMERGENCY SERVICES; FUNDING; HEALTH SERVICES; HIGHER EDUCATION; IMMIGRATION; INSURANCE"], "abstracts": [], "other_titles": [], "other_identifiers": [], "actions": [{"description": "Ref To Com On Rules, Calendar, and Operations of the House", "date": "2025-04-14", "organization_id": "~{\"classification\": \"lower\"}", "classification": ["referral-committee"], "related_entities": []}, {"description": "Passed 1st Reading", "date": "2025-04-14", "organization_id": "~{\"classification\": \"lower\"}", "classification": ["reading-1"], "related_entities": []}, {"description": "Filed", "date": "2025-04-10", "organization_id": "~{\"classification\": \"lower\"}", "classification": ["introduction"], "related_entities": []}], "sponsorships": [{"name": "Hawkins", "classification": "cosponsor", "entity_type": "person", "primary": false, "person_id": "~{\"name\": \"Hawkins\"}", "organization_id": null}, {"name": "Baker", "classification": "cosponsor", "entity_type": "person", "primary": false, "person_id": "~{\"name\": \"Baker\"}", "organization_id": null}, {"name": "Budd", "classification": "cosponsor", "entity_type": "person", "primary": false, "person_id": "~{\"name\": \"Budd\"}", "organization_id": null}, {"name": "Cervania", "classification": "cosponsor", "entity_type": "person", "primary": false, "person_id": "~{\"name\": \"Cervania\"}", "organization_id": null}, {"name": "Harrison", "classification": "cosponsor", "entity_type": "person", "primary": false, "person_id": "~{\"name\": \"Harrison\"}", "organization_id": null}], "related_bills": [], "versions": [{"note": "Filed", "links": [{"url": "https://www.ncleg.gov/Sessions/2025/Bills/House/PDF/H977v0.pdf", "media_type": "application/pdf"}], "date": "", "classification": ""}, {"note": "Edition 1", "links": [{"url": "https://www.ncleg.gov/Sessions/2025/Bills/House/PDF/H977v1.pdf", "media_type": "application/pdf"}], "date": "", "classification": ""}], "documents": [], "citations": [], "sources": [{"url": "https://www.ncleg.gov/BillLookUp/2025/H977", "note": ""}], "extras": {}, "jurisdiction": {"id": "ocd-jurisdiction/country:us/state:nc/government", "name": "North Carolina", "classification": "state", "division_id": "ocd-division/country:us/state:nc"}, "scraped_at": "2025-07-28T19:02:50+00:00", "_id": "74eb31bc-6be5-11f0-9237-f685d79cdd2c"}