{"legislative_session": "2025", "identifier": "SB 417", "title": "Posting of State Costs.", "from_organization": "~{\"classification\": \"upper\"}", "classification": ["bill"], "subject": ["ADMINISTRATION DEPT.; BUDGETING; CONTRACTS; GENERAL ASSEMBLY; INFORMATION TECHNOLOGY; INTERNET; LEGISLATIVE SERVICES OFFICE; PUBLIC; PUBLIC RECORDS; PURCHASING; TELECOMMUNICATIONS; TELESERVICES; RECORDS; ELECTRONIC GOVERNMENT"], "abstracts": [], "other_titles": [], "other_identifiers": [], "actions": [{"description": "Ref To Com On Rules and Operations of the Senate", "date": "2025-03-25", "organization_id": "~{\"classification\": \"upper\"}", "classification": ["referral-committee"], "related_entities": []}, {"description": "Passed 1st Reading", "date": "2025-03-25", "organization_id": "~{\"classification\": \"upper\"}", "classification": ["reading-1"], "related_entities": []}, {"description": "Filed", "date": "2025-03-24", "organization_id": "~{\"classification\": \"upper\"}", "classification": ["introduction"], "related_entities": []}], "sponsorships": [{"name": "Burgin", "classification": "cosponsor", "entity_type": "person", "primary": false, "person_id": "~{\"name\": \"Burgin\"}", "organization_id": null}], "related_bills": [], "versions": [{"note": "Filed", "links": [{"url": "https://www.ncleg.gov/Sessions/2025/Bills/Senate/PDF/S417v0.pdf", "media_type": "application/pdf"}], "date": "", "classification": ""}, {"note": "Edition 1", "links": [{"url": "https://www.ncleg.gov/Sessions/2025/Bills/Senate/PDF/S417v1.pdf", "media_type": "application/pdf"}], "date": "", "classification": ""}], "documents": [], "citations": [], "sources": [{"url": "https://www.ncleg.gov/BillLookUp/2025/S417", "note": ""}], "extras": {}, "jurisdiction": {"id": "ocd-jurisdiction/country:us/state:nc/government", "name": "North Carolina", "classification": "state", "division_id": "ocd-division/country:us/state:nc"}, "scraped_at": "2025-07-28T18:11:39+00:00", "_id": "4ede26a2-6bde-11f0-821e-1a84e89b82ea"}